just_agents/__init__.py
just_agents/meta/__init__.py
just_agents/py.typed
just_agents-0.8.8.dist-info/METADATA
just_agents-0.8.8.dist-info/WHEEL
just_agents-0.8.8.dist-info/entry_points.txt
just_agents-0.8.8.dist-info/licenses/LICENSE
just_agents-0.8.8.dist-info/RECORD
