Metadata-Version: 2.4
Name: just-agents
Version: 0.8.8
Summary: Just Agents
License: Apache 2.0
License-File: LICENSE
Keywords: python,llm,agents,AI,machine-learning
Author: Alex Karmazin
Author-email: karmazinalex@gmail.com
Maintainer: Anton Kulaga
Maintainer-email: antonkulaga@gmail.com
Requires-Python: >=3.10,<3.15
Classifier: License :: Other/Proprietary License
Classifier: Programming Language :: Python :: 3
Classifier: Programming Language :: Python :: 3.10
Classifier: Programming Language :: Python :: 3.11
Classifier: Programming Language :: Python :: 3.12
Classifier: Programming Language :: Python :: 3.13
Classifier: Programming Language :: Python :: 3.14
Requires-Dist: just-agents-coding
Requires-Dist: just-agents-core
Requires-Dist: just-agents-examples
Requires-Dist: just-agents-router
Requires-Dist: just-agents-tools
Requires-Dist: just-agents-web
Requires-Dist: pyrsistent (>=0.20.0,<0.21.0)
